LICENSE
MANIFEST.in
README.md
description.rst
setup.py
mosaik_docker/__init__.py
mosaik_docker/_config.py
mosaik_docker/starter.py
mosaik_docker.egg-info/PKG-INFO
mosaik_docker.egg-info/SOURCES.txt
mosaik_docker.egg-info/dependency_links.txt
mosaik_docker.egg-info/entry_points.txt
mosaik_docker.egg-info/requires.txt
mosaik_docker.egg-info/top_level.txt
mosaik_docker/cli/__init__.py
mosaik_docker/cli/build_sim_setup.py
mosaik_docker/cli/cancel_sim.py
mosaik_docker/cli/check_sim_setup.py
mosaik_docker/cli/clear_sim.py
mosaik_docker/cli/configure_sim_setup.py
mosaik_docker/cli/create_sim_setup.py
mosaik_docker/cli/delete_sim_setup.py
mosaik_docker/cli/get_sim_ids.py
mosaik_docker/cli/get_sim_results.py
mosaik_docker/cli/get_sim_setup_root.py
mosaik_docker/cli/get_sim_status.py
mosaik_docker/cli/start_sim.py
mosaik_docker/sim_setup_template/cookiecutter.json
mosaik_docker/sim_setup_template/{{cookiecutter.directory_name}}/README.md
mosaik_docker/sim_setup_template/{{cookiecutter.directory_name}}/mosaik-docker.json
mosaik_docker/sim_setup_template/{{cookiecutter.directory_name}}/dockerfiles/Dockerfile_main
mosaik_docker/util/__init__.py
mosaik_docker/util/config_data.py
mosaik_docker/util/create_unique_id.py
mosaik_docker/util/execute.py
mosaik_docker/util/flatten_list.py
mosaik_docker/util/get_default_docker_host.py