Metadata-Version: 2.1
Name: mosaik-docker
Version: 0.2.0
Summary: This package eases the deployment of the mosaik co-simulation framework with Docker.
Home-page: https://mosaik-docker.readthedocs.io
Maintainer: ERIGrid 2.0 development team
Maintainer-email: edmund.widl@ait.ac.at
License: BSD 3-Clause License
Keywords: mosaik,Docker
Platform: any
Classifier: Development Status :: 4 - Beta
Classifier: Environment :: Console
Classifier: Intended Audience :: Science/Research
Classifier: Intended Audience :: Developers
Classifier: License :: OSI Approved :: BSD License
Classifier: Natural Language :: English
Classifier: Operating System :: OS Independent
Classifier: Programming Language :: Python
Classifier: Topic :: Scientific/Engineering
License-File: LICENSE
Requires-Dist: cookiecutter
Requires-Dist: mosaik~=2.6.0
Requires-Dist: strenum
